<?xml version="1.0" encoding="UTF-8"?>
<?xml-stylesheet href="CoreNLP-to-HTML.xsl" type="text/xsl"?>
<root>
  <document>
    <sentences>
      <sentence id="1">
        <tokens>
          <token id="1">
            <word>THE</word>
            <lemma>the</lemma>
            <CharacterOffsetBegin>0</CharacterOffsetBegin>
            <CharacterOffsetEnd>3</CharacterOffsetEnd>
            <POS>DT</POS>
            <NER>O</NER>
          </token>
          <token id="2">
            <word>hotel</word>
            <lemma>hotel</lemma>
            <CharacterOffsetBegin>4</CharacterOffsetBegin>
            <CharacterOffsetEnd>9</CharacterOffsetEnd>
            <POS>NN</POS>
            <NER>O</NER>
          </token>
          <token id="3">
            <word>''</word>
            <lemma>''</lemma>
            <CharacterOffsetBegin>10</CharacterOffsetBegin>
            <CharacterOffsetEnd>12</CharacterOffsetEnd>
            <POS>''</POS>
            <NER>O</NER>
          </token>
          <token id="4">
            <word>bed</word>
            <lemma>bed</lemma>
            <CharacterOffsetBegin>12</CharacterOffsetBegin>
            <CharacterOffsetEnd>15</CharacterOffsetEnd>
            <POS>NN</POS>
            <NER>O</NER>
          </token>
          <token id="5">
            <word>wars</word>
            <lemma>war</lemma>
            <CharacterOffsetBegin>16</CharacterOffsetBegin>
            <CharacterOffsetEnd>20</CharacterOffsetEnd>
            <POS>NNS</POS>
            <NER>O</NER>
          </token>
          <token id="6">
            <word>''</word>
            <lemma>''</lemma>
            <CharacterOffsetBegin>20</CharacterOffsetBegin>
            <CharacterOffsetEnd>22</CharacterOffsetEnd>
            <POS>''</POS>
            <NER>O</NER>
          </token>
          <token id="7">
            <word>are</word>
            <lemma>be</lemma>
            <CharacterOffsetBegin>23</CharacterOffsetBegin>
            <CharacterOffsetEnd>26</CharacterOffsetEnd>
            <POS>VBP</POS>
            <NER>O</NER>
          </token>
          <token id="8">
            <word>over</word>
            <lemma>over</lemma>
            <CharacterOffsetBegin>27</CharacterOffsetBegin>
            <CharacterOffsetEnd>31</CharacterOffsetEnd>
            <POS>IN</POS>
            <NER>O</NER>
          </token>
          <token id="9">
            <word>.</word>
            <lemma>.</lemma>
            <CharacterOffsetBegin>31</CharacterOffsetBegin>
            <CharacterOffsetEnd>32</CharacterOffsetEnd>
            <POS>.</POS>
            <NER>O</NER>
          </token>
        </tokens>
      </sentence>
      <sentence id="2">
        <tokens>
          <token id="1">
            <word>But</word>
            <lemma>but</lemma>
            <CharacterOffsetBegin>33</CharacterOffsetBegin>
            <CharacterOffsetEnd>36</CharacterOffsetEnd>
            <POS>CC</POS>
            <NER>O</NER>
          </token>
          <token id="2">
            <word>are</word>
            <lemma>be</lemma>
            <CharacterOffsetBegin>37</CharacterOffsetBegin>
            <CharacterOffsetEnd>40</CharacterOffsetEnd>
            <POS>VBP</POS>
            <NER>O</NER>
          </token>
          <token id="3">
            <word>business</word>
            <lemma>business</lemma>
            <CharacterOffsetBegin>41</CharacterOffsetBegin>
            <CharacterOffsetEnd>49</CharacterOffsetEnd>
            <POS>NN</POS>
            <NER>O</NER>
          </token>
          <token id="4">
            <word>travelers</word>
            <lemma>traveler</lemma>
            <CharacterOffsetBegin>50</CharacterOffsetBegin>
            <CharacterOffsetEnd>59</CharacterOffsetEnd>
            <POS>NNS</POS>
            <NER>O</NER>
          </token>
          <token id="5">
            <word>the</word>
            <lemma>the</lemma>
            <CharacterOffsetBegin>60</CharacterOffsetBegin>
            <CharacterOffsetEnd>63</CharacterOffsetEnd>
            <POS>DT</POS>
            <NER>O</NER>
          </token>
          <token id="6">
            <word>winners</word>
            <lemma>winner</lemma>
            <CharacterOffsetBegin>64</CharacterOffsetBegin>
            <CharacterOffsetEnd>71</CharacterOffsetEnd>
            <POS>NNS</POS>
            <NER>O</NER>
          </token>
          <token id="7">
            <word>?</word>
            <lemma>?</lemma>
            <CharacterOffsetBegin>71</CharacterOffsetBegin>
            <CharacterOffsetEnd>72</CharacterOffsetEnd>
            <POS>.</POS>
            <NER>O</NER>
          </token>
        </tokens>
      </sentence>
      <sentence id="3">
        <tokens>
          <token id="1">
            <word>Most</word>
            <lemma>most</lemma>
            <CharacterOffsetBegin>73</CharacterOffsetBegin>
            <CharacterOffsetEnd>77</CharacterOffsetEnd>
            <POS>JJS</POS>
            <NER>O</NER>
          </token>
          <token id="2">
            <word>frequent</word>
            <lemma>frequent</lemma>
            <CharacterOffsetBegin>78</CharacterOffsetBegin>
            <CharacterOffsetEnd>86</CharacterOffsetEnd>
            <POS>JJ</POS>
            <NER>O</NER>
          </token>
          <token id="3">
            <word>travelers</word>
            <lemma>traveler</lemma>
            <CharacterOffsetBegin>87</CharacterOffsetBegin>
            <CharacterOffsetEnd>96</CharacterOffsetEnd>
            <POS>NNS</POS>
            <NER>O</NER>
          </token>
          <token id="4">
            <word>would</word>
            <lemma>would</lemma>
            <CharacterOffsetBegin>97</CharacterOffsetBegin>
            <CharacterOffsetEnd>102</CharacterOffsetEnd>
            <POS>MD</POS>
            <NER>O</NER>
          </token>
          <token id="5">
            <word>probably</word>
            <lemma>probably</lemma>
            <CharacterOffsetBegin>103</CharacterOffsetBegin>
            <CharacterOffsetEnd>111</CharacterOffsetEnd>
            <POS>RB</POS>
            <NER>O</NER>
          </token>
          <token id="6">
            <word>say</word>
            <lemma>say</lemma>
            <CharacterOffsetBegin>112</CharacterOffsetBegin>
            <CharacterOffsetEnd>115</CharacterOffsetEnd>
            <POS>VB</POS>
            <NER>O</NER>
          </token>
          <token id="7">
            <word>they</word>
            <lemma>they</lemma>
            <CharacterOffsetBegin>116</CharacterOffsetBegin>
            <CharacterOffsetEnd>120</CharacterOffsetEnd>
            <POS>PRP</POS>
            <NER>O</NER>
          </token>
          <token id="8">
            <word>are</word>
            <lemma>be</lemma>
            <CharacterOffsetBegin>121</CharacterOffsetBegin>
            <CharacterOffsetEnd>124</CharacterOffsetEnd>
            <POS>VBP</POS>
            <NER>O</NER>
          </token>
          <token id="9">
            <word>,</word>
            <lemma>,</lemma>
            <CharacterOffsetBegin>124</CharacterOffsetBegin>
            <CharacterOffsetEnd>125</CharacterOffsetEnd>
            <POS>,</POS>
            <NER>O</NER>
          </token>
          <token id="10">
            <word>citing</word>
            <lemma>cite</lemma>
            <CharacterOffsetBegin>126</CharacterOffsetBegin>
            <CharacterOffsetEnd>132</CharacterOffsetEnd>
            <POS>VBG</POS>
            <NER>O</NER>
          </token>
          <token id="11">
            <word>the</word>
            <lemma>the</lemma>
            <CharacterOffsetBegin>133</CharacterOffsetBegin>
            <CharacterOffsetEnd>136</CharacterOffsetEnd>
            <POS>DT</POS>
            <NER>O</NER>
          </token>
          <token id="12">
            <word>remarkable</word>
            <lemma>remarkable</lemma>
            <CharacterOffsetBegin>137</CharacterOffsetBegin>
            <CharacterOffsetEnd>147</CharacterOffsetEnd>
            <POS>JJ</POS>
            <NER>O</NER>
          </token>
          <token id="13">
            <word>evolution</word>
            <lemma>evolution</lemma>
            <CharacterOffsetBegin>148</CharacterOffsetBegin>
            <CharacterOffsetEnd>157</CharacterOffsetEnd>
            <POS>NN</POS>
            <NER>O</NER>
          </token>
          <token id="14">
            <word>of</word>
            <lemma>of</lemma>
            <CharacterOffsetBegin>158</CharacterOffsetBegin>
            <CharacterOffsetEnd>160</CharacterOffsetEnd>
            <POS>IN</POS>
            <NER>O</NER>
          </token>
          <token id="15">
            <word>hotel</word>
            <lemma>hotel</lemma>
            <CharacterOffsetBegin>161</CharacterOffsetBegin>
            <CharacterOffsetEnd>166</CharacterOffsetEnd>
            <POS>NN</POS>
            <NER>O</NER>
          </token>
          <token id="16">
            <word>beds</word>
            <lemma>bed</lemma>
            <CharacterOffsetBegin>167</CharacterOffsetBegin>
            <CharacterOffsetEnd>171</CharacterOffsetEnd>
            <POS>NNS</POS>
            <NER>O</NER>
          </token>
          <token id="17">
            <word>from</word>
            <lemma>from</lemma>
            <CharacterOffsetBegin>172</CharacterOffsetBegin>
            <CharacterOffsetEnd>176</CharacterOffsetEnd>
            <POS>IN</POS>
            <NER>O</NER>
          </token>
          <token id="18">
            <word>the</word>
            <lemma>the</lemma>
            <CharacterOffsetBegin>177</CharacterOffsetBegin>
            <CharacterOffsetEnd>180</CharacterOffsetEnd>
            <POS>DT</POS>
            <NER>O</NER>
          </token>
          <token id="19">
            <word>no-nonsense</word>
            <lemma>no-nonsense</lemma>
            <CharacterOffsetBegin>181</CharacterOffsetBegin>
            <CharacterOffsetEnd>192</CharacterOffsetEnd>
            <POS>JJ</POS>
            <NER>O</NER>
          </token>
          <token id="20">
            <word>affairs</word>
            <lemma>affair</lemma>
            <CharacterOffsetBegin>193</CharacterOffsetBegin>
            <CharacterOffsetEnd>200</CharacterOffsetEnd>
            <POS>NNS</POS>
            <NER>O</NER>
          </token>
          <token id="21">
            <word>of</word>
            <lemma>of</lemma>
            <CharacterOffsetBegin>201</CharacterOffsetBegin>
            <CharacterOffsetEnd>203</CharacterOffsetEnd>
            <POS>IN</POS>
            <NER>O</NER>
          </token>
          <token id="22">
            <word>the</word>
            <lemma>the</lemma>
            <CharacterOffsetBegin>204</CharacterOffsetBegin>
            <CharacterOffsetEnd>207</CharacterOffsetEnd>
            <POS>DT</POS>
            <NER>O</NER>
          </token>
          <token id="23">
            <word>late</word>
            <lemma>late</lemma>
            <CharacterOffsetBegin>208</CharacterOffsetBegin>
            <CharacterOffsetEnd>212</CharacterOffsetEnd>
            <POS>JJ</POS>
            <NER>DATE</NER>
            <NormalizedNER>1990</NormalizedNER>
            <Timex tid="t1" type="DATE">1990</Timex>
          </token>
          <token id="24">
            <word>1990</word>
            <lemma>1990</lemma>
            <CharacterOffsetBegin>213</CharacterOffsetBegin>
            <CharacterOffsetEnd>217</CharacterOffsetEnd>
            <POS>CD</POS>
            <NER>DATE</NER>
            <NormalizedNER>1990</NormalizedNER>
            <Timex tid="t1" type="DATE">1990</Timex>
          </token>
          <token id="25">
            <word>'s</word>
            <lemma>'s</lemma>
            <CharacterOffsetBegin>217</CharacterOffsetBegin>
            <CharacterOffsetEnd>219</CharacterOffsetEnd>
            <POS>POS</POS>
            <NER>O</NER>
          </token>
          <token id="26">
            <word>--</word>
            <lemma>--</lemma>
            <CharacterOffsetBegin>220</CharacterOffsetBegin>
            <CharacterOffsetEnd>222</CharacterOffsetEnd>
            <POS>:</POS>
            <NER>O</NER>
          </token>
          <token id="27">
            <word>just</word>
            <lemma>just</lemma>
            <CharacterOffsetBegin>223</CharacterOffsetBegin>
            <CharacterOffsetEnd>227</CharacterOffsetEnd>
            <POS>RB</POS>
            <NER>O</NER>
          </token>
          <token id="28">
            <word>mattresses</word>
            <lemma>mattress</lemma>
            <CharacterOffsetBegin>228</CharacterOffsetBegin>
            <CharacterOffsetEnd>238</CharacterOffsetEnd>
            <POS>NNS</POS>
            <NER>O</NER>
          </token>
          <token id="29">
            <word>,</word>
            <lemma>,</lemma>
            <CharacterOffsetBegin>238</CharacterOffsetBegin>
            <CharacterOffsetEnd>239</CharacterOffsetEnd>
            <POS>,</POS>
            <NER>O</NER>
          </token>
          <token id="30">
            <word>sheets</word>
            <lemma>sheet</lemma>
            <CharacterOffsetBegin>240</CharacterOffsetBegin>
            <CharacterOffsetEnd>246</CharacterOffsetEnd>
            <POS>NNS</POS>
            <NER>O</NER>
          </token>
          <token id="31">
            <word>and</word>
            <lemma>and</lemma>
            <CharacterOffsetBegin>247</CharacterOffsetBegin>
            <CharacterOffsetEnd>250</CharacterOffsetEnd>
            <POS>CC</POS>
            <NER>O</NER>
          </token>
          <token id="32">
            <word>bedspreads</word>
            <lemma>bedspread</lemma>
            <CharacterOffsetBegin>251</CharacterOffsetBegin>
            <CharacterOffsetEnd>261</CharacterOffsetEnd>
            <POS>NNS</POS>
            <NER>O</NER>
          </token>
          <token id="33">
            <word>--</word>
            <lemma>--</lemma>
            <CharacterOffsetBegin>262</CharacterOffsetBegin>
            <CharacterOffsetEnd>264</CharacterOffsetEnd>
            <POS>:</POS>
            <NER>O</NER>
          </token>
          <token id="34">
            <word>to</word>
            <lemma>to</lemma>
            <CharacterOffsetBegin>265</CharacterOffsetBegin>
            <CharacterOffsetEnd>267</CharacterOffsetEnd>
            <POS>TO</POS>
            <NER>O</NER>
          </token>
          <token id="35">
            <word>the</word>
            <lemma>the</lemma>
            <CharacterOffsetBegin>268</CharacterOffsetBegin>
            <CharacterOffsetEnd>271</CharacterOffsetEnd>
            <POS>DT</POS>
            <NER>O</NER>
          </token>
          <token id="36">
            <word>superpremium</word>
            <lemma>superpremium</lemma>
            <CharacterOffsetBegin>272</CharacterOffsetBegin>
            <CharacterOffsetEnd>284</CharacterOffsetEnd>
            <POS>JJ</POS>
            <NER>O</NER>
          </token>
          <token id="37">
            <word>sleep</word>
            <lemma>sleep</lemma>
            <CharacterOffsetBegin>285</CharacterOffsetBegin>
            <CharacterOffsetEnd>290</CharacterOffsetEnd>
            <POS>NN</POS>
            <NER>O</NER>
          </token>
          <token id="38">
            <word>''</word>
            <lemma>''</lemma>
            <CharacterOffsetBegin>291</CharacterOffsetBegin>
            <CharacterOffsetEnd>293</CharacterOffsetEnd>
            <POS>''</POS>
            <NER>O</NER>
          </token>
          <token id="39">
            <word>experiences</word>
            <lemma>experience</lemma>
            <CharacterOffsetBegin>293</CharacterOffsetBegin>
            <CharacterOffsetEnd>304</CharacterOffsetEnd>
            <POS>NNS</POS>
            <NER>O</NER>
          </token>
          <token id="40">
            <word>''</word>
            <lemma>''</lemma>
            <CharacterOffsetBegin>304</CharacterOffsetBegin>
            <CharacterOffsetEnd>306</CharacterOffsetEnd>
            <POS>''</POS>
            <NER>O</NER>
          </token>
          <token id="41">
            <word>of</word>
            <lemma>of</lemma>
            <CharacterOffsetBegin>307</CharacterOffsetBegin>
            <CharacterOffsetEnd>309</CharacterOffsetEnd>
            <POS>IN</POS>
            <NER>O</NER>
          </token>
          <token id="42">
            <word>today</word>
            <lemma>today</lemma>
            <CharacterOffsetBegin>310</CharacterOffsetBegin>
            <CharacterOffsetEnd>315</CharacterOffsetEnd>
            <POS>NN</POS>
            <NER>DATE</NER>
            <NormalizedNER>THIS P1D</NormalizedNER>
            <Timex tid="t2" type="DATE"/>
          </token>
          <token id="43">
            <word>.</word>
            <lemma>.</lemma>
            <CharacterOffsetBegin>315</CharacterOffsetBegin>
            <CharacterOffsetEnd>316</CharacterOffsetEnd>
            <POS>.</POS>
            <NER>O</NER>
          </token>
        </tokens>
      </sentence>
    </sentences>
  </document>
</root>
