<?xml version="1.0" encoding="UTF-8"?>
<?xml-stylesheet href="CoreNLP-to-HTML.xsl" type="text/xsl"?>
<root>
  <document>
    <sentences>
      <sentence id="1">
        <tokens>
          <token id="1">
            <word>Carl</word>
            <lemma>Carl</lemma>
            <CharacterOffsetBegin>0</CharacterOffsetBegin>
            <CharacterOffsetEnd>4</CharacterOffsetEnd>
            <POS>NNP</POS>
            <NER>PERSON</NER>
          </token>
          <token id="2">
            <word>C.</word>
            <lemma>C.</lemma>
            <CharacterOffsetBegin>5</CharacterOffsetBegin>
            <CharacterOffsetEnd>7</CharacterOffsetEnd>
            <POS>NNP</POS>
            <NER>PERSON</NER>
          </token>
          <token id="3">
            <word>Icahn</word>
            <lemma>Icahn</lemma>
            <CharacterOffsetBegin>8</CharacterOffsetBegin>
            <CharacterOffsetEnd>13</CharacterOffsetEnd>
            <POS>NNP</POS>
            <NER>PERSON</NER>
          </token>
          <token id="4">
            <word>said</word>
            <lemma>say</lemma>
            <CharacterOffsetBegin>14</CharacterOffsetBegin>
            <CharacterOffsetEnd>18</CharacterOffsetEnd>
            <POS>VBD</POS>
            <NER>O</NER>
          </token>
          <token id="5">
            <word>yesterday</word>
            <lemma>yesterday</lemma>
            <CharacterOffsetBegin>19</CharacterOffsetBegin>
            <CharacterOffsetEnd>28</CharacterOffsetEnd>
            <POS>NN</POS>
            <NER>DATE</NER>
            <NormalizedNER>OFFSET P-1D</NormalizedNER>
            <Timex tid="t1" type="DATE"/>
          </token>
          <token id="6">
            <word>that</word>
            <lemma>that</lemma>
            <CharacterOffsetBegin>29</CharacterOffsetBegin>
            <CharacterOffsetEnd>33</CharacterOffsetEnd>
            <POS>IN</POS>
            <NER>O</NER>
          </token>
          <token id="7">
            <word>he</word>
            <lemma>he</lemma>
            <CharacterOffsetBegin>34</CharacterOffsetBegin>
            <CharacterOffsetEnd>36</CharacterOffsetEnd>
            <POS>PRP</POS>
            <NER>O</NER>
          </token>
          <token id="8">
            <word>had</word>
            <lemma>have</lemma>
            <CharacterOffsetBegin>37</CharacterOffsetBegin>
            <CharacterOffsetEnd>40</CharacterOffsetEnd>
            <POS>VBD</POS>
            <NER>O</NER>
          </token>
          <token id="9">
            <word>recruited</word>
            <lemma>recruit</lemma>
            <CharacterOffsetBegin>41</CharacterOffsetBegin>
            <CharacterOffsetEnd>50</CharacterOffsetEnd>
            <POS>VBN</POS>
            <NER>O</NER>
          </token>
          <token id="10">
            <word>Frank</word>
            <lemma>Frank</lemma>
            <CharacterOffsetBegin>51</CharacterOffsetBegin>
            <CharacterOffsetEnd>56</CharacterOffsetEnd>
            <POS>NNP</POS>
            <NER>PERSON</NER>
          </token>
          <token id="11">
            <word>J.</word>
            <lemma>J.</lemma>
            <CharacterOffsetBegin>57</CharacterOffsetBegin>
            <CharacterOffsetEnd>59</CharacterOffsetEnd>
            <POS>NNP</POS>
            <NER>PERSON</NER>
          </token>
          <token id="12">
            <word>Biondi</word>
            <lemma>Biondi</lemma>
            <CharacterOffsetBegin>60</CharacterOffsetBegin>
            <CharacterOffsetEnd>66</CharacterOffsetEnd>
            <POS>NNP</POS>
            <NER>PERSON</NER>
          </token>
          <token id="13">
            <word>Jr.</word>
            <lemma>Jr.</lemma>
            <CharacterOffsetBegin>67</CharacterOffsetBegin>
            <CharacterOffsetEnd>70</CharacterOffsetEnd>
            <POS>NNP</POS>
            <NER>PERSON</NER>
          </token>
          <token id="14">
            <word>,</word>
            <lemma>,</lemma>
            <CharacterOffsetBegin>70</CharacterOffsetBegin>
            <CharacterOffsetEnd>71</CharacterOffsetEnd>
            <POS>,</POS>
            <NER>O</NER>
          </token>
          <token id="15">
            <word>the</word>
            <lemma>the</lemma>
            <CharacterOffsetBegin>72</CharacterOffsetBegin>
            <CharacterOffsetEnd>75</CharacterOffsetEnd>
            <POS>DT</POS>
            <NER>O</NER>
          </token>
          <token id="16">
            <word>former</word>
            <lemma>former</lemma>
            <CharacterOffsetBegin>76</CharacterOffsetBegin>
            <CharacterOffsetEnd>82</CharacterOffsetEnd>
            <POS>JJ</POS>
            <NER>O</NER>
          </token>
          <token id="17">
            <word>chief</word>
            <lemma>chief</lemma>
            <CharacterOffsetBegin>83</CharacterOffsetBegin>
            <CharacterOffsetEnd>88</CharacterOffsetEnd>
            <POS>JJ</POS>
            <NER>O</NER>
          </token>
          <token id="18">
            <word>executive</word>
            <lemma>executive</lemma>
            <CharacterOffsetBegin>89</CharacterOffsetBegin>
            <CharacterOffsetEnd>98</CharacterOffsetEnd>
            <POS>NN</POS>
            <NER>O</NER>
          </token>
          <token id="19">
            <word>of</word>
            <lemma>of</lemma>
            <CharacterOffsetBegin>99</CharacterOffsetBegin>
            <CharacterOffsetEnd>101</CharacterOffsetEnd>
            <POS>IN</POS>
            <NER>O</NER>
          </token>
          <token id="20">
            <word>Viacom</word>
            <lemma>Viacom</lemma>
            <CharacterOffsetBegin>102</CharacterOffsetBegin>
            <CharacterOffsetEnd>108</CharacterOffsetEnd>
            <POS>NNP</POS>
            <NER>ORGANIZATION</NER>
          </token>
          <token id="21">
            <word>and</word>
            <lemma>and</lemma>
            <CharacterOffsetBegin>109</CharacterOffsetBegin>
            <CharacterOffsetEnd>112</CharacterOffsetEnd>
            <POS>CC</POS>
            <NER>O</NER>
          </token>
          <token id="22">
            <word>Universal</word>
            <lemma>Universal</lemma>
            <CharacterOffsetBegin>113</CharacterOffsetBegin>
            <CharacterOffsetEnd>122</CharacterOffsetEnd>
            <POS>NNP</POS>
            <NER>ORGANIZATION</NER>
          </token>
          <token id="23">
            <word>Studios</word>
            <lemma>Studios</lemma>
            <CharacterOffsetBegin>123</CharacterOffsetBegin>
            <CharacterOffsetEnd>130</CharacterOffsetEnd>
            <POS>NNP</POS>
            <NER>ORGANIZATION</NER>
          </token>
          <token id="24">
            <word>,</word>
            <lemma>,</lemma>
            <CharacterOffsetBegin>130</CharacterOffsetBegin>
            <CharacterOffsetEnd>131</CharacterOffsetEnd>
            <POS>,</POS>
            <NER>O</NER>
          </token>
          <token id="25">
            <word>to</word>
            <lemma>to</lemma>
            <CharacterOffsetBegin>132</CharacterOffsetBegin>
            <CharacterOffsetEnd>134</CharacterOffsetEnd>
            <POS>TO</POS>
            <NER>O</NER>
          </token>
          <token id="26">
            <word>become</word>
            <lemma>become</lemma>
            <CharacterOffsetBegin>135</CharacterOffsetBegin>
            <CharacterOffsetEnd>141</CharacterOffsetEnd>
            <POS>VB</POS>
            <NER>O</NER>
          </token>
          <token id="27">
            <word>Time</word>
            <lemma>Time</lemma>
            <CharacterOffsetBegin>142</CharacterOffsetBegin>
            <CharacterOffsetEnd>146</CharacterOffsetEnd>
            <POS>NNP</POS>
            <NER>ORGANIZATION</NER>
          </token>
          <token id="28">
            <word>Warner</word>
            <lemma>Warner</lemma>
            <CharacterOffsetBegin>147</CharacterOffsetBegin>
            <CharacterOffsetEnd>153</CharacterOffsetEnd>
            <POS>NNP</POS>
            <NER>ORGANIZATION</NER>
          </token>
          <token id="29">
            <word>'s</word>
            <lemma>'s</lemma>
            <CharacterOffsetBegin>153</CharacterOffsetBegin>
            <CharacterOffsetEnd>155</CharacterOffsetEnd>
            <POS>POS</POS>
            <NER>O</NER>
          </token>
          <token id="30">
            <word>chairman</word>
            <lemma>chairman</lemma>
            <CharacterOffsetBegin>156</CharacterOffsetBegin>
            <CharacterOffsetEnd>164</CharacterOffsetEnd>
            <POS>NN</POS>
            <NER>O</NER>
          </token>
          <token id="31">
            <word>and</word>
            <lemma>and</lemma>
            <CharacterOffsetBegin>165</CharacterOffsetBegin>
            <CharacterOffsetEnd>168</CharacterOffsetEnd>
            <POS>CC</POS>
            <NER>O</NER>
          </token>
          <token id="32">
            <word>chief</word>
            <lemma>chief</lemma>
            <CharacterOffsetBegin>169</CharacterOffsetBegin>
            <CharacterOffsetEnd>174</CharacterOffsetEnd>
            <POS>JJ</POS>
            <NER>O</NER>
          </token>
          <token id="33">
            <word>executive</word>
            <lemma>executive</lemma>
            <CharacterOffsetBegin>175</CharacterOffsetBegin>
            <CharacterOffsetEnd>184</CharacterOffsetEnd>
            <POS>NN</POS>
            <NER>O</NER>
          </token>
          <token id="34">
            <word>if</word>
            <lemma>if</lemma>
            <CharacterOffsetBegin>185</CharacterOffsetBegin>
            <CharacterOffsetEnd>187</CharacterOffsetEnd>
            <POS>IN</POS>
            <NER>O</NER>
          </token>
          <token id="35">
            <word>Mr.</word>
            <lemma>Mr.</lemma>
            <CharacterOffsetBegin>188</CharacterOffsetBegin>
            <CharacterOffsetEnd>191</CharacterOffsetEnd>
            <POS>NNP</POS>
            <NER>PERSON</NER>
          </token>
          <token id="36">
            <word>Icahn</word>
            <lemma>Icahn</lemma>
            <CharacterOffsetBegin>192</CharacterOffsetBegin>
            <CharacterOffsetEnd>197</CharacterOffsetEnd>
            <POS>NNP</POS>
            <NER>PERSON</NER>
          </token>
          <token id="37">
            <word>prevailed</word>
            <lemma>prevail</lemma>
            <CharacterOffsetBegin>198</CharacterOffsetBegin>
            <CharacterOffsetEnd>207</CharacterOffsetEnd>
            <POS>VBD</POS>
            <NER>O</NER>
          </token>
          <token id="38">
            <word>in</word>
            <lemma>in</lemma>
            <CharacterOffsetBegin>208</CharacterOffsetBegin>
            <CharacterOffsetEnd>210</CharacterOffsetEnd>
            <POS>IN</POS>
            <NER>O</NER>
          </token>
          <token id="39">
            <word>a</word>
            <lemma>a</lemma>
            <CharacterOffsetBegin>211</CharacterOffsetBegin>
            <CharacterOffsetEnd>212</CharacterOffsetEnd>
            <POS>DT</POS>
            <NER>O</NER>
          </token>
          <token id="40">
            <word>planned</word>
            <lemma>plan</lemma>
            <CharacterOffsetBegin>213</CharacterOffsetBegin>
            <CharacterOffsetEnd>220</CharacterOffsetEnd>
            <POS>VBN</POS>
            <NER>O</NER>
          </token>
          <token id="41">
            <word>proxy</word>
            <lemma>proxy</lemma>
            <CharacterOffsetBegin>221</CharacterOffsetBegin>
            <CharacterOffsetEnd>226</CharacterOffsetEnd>
            <POS>NN</POS>
            <NER>O</NER>
          </token>
          <token id="42">
            <word>fight</word>
            <lemma>fight</lemma>
            <CharacterOffsetBegin>227</CharacterOffsetBegin>
            <CharacterOffsetEnd>232</CharacterOffsetEnd>
            <POS>NN</POS>
            <NER>O</NER>
          </token>
          <token id="43">
            <word>for</word>
            <lemma>for</lemma>
            <CharacterOffsetBegin>233</CharacterOffsetBegin>
            <CharacterOffsetEnd>236</CharacterOffsetEnd>
            <POS>IN</POS>
            <NER>O</NER>
          </token>
          <token id="44">
            <word>control</word>
            <lemma>control</lemma>
            <CharacterOffsetBegin>237</CharacterOffsetBegin>
            <CharacterOffsetEnd>244</CharacterOffsetEnd>
            <POS>NN</POS>
            <NER>O</NER>
          </token>
          <token id="45">
            <word>of</word>
            <lemma>of</lemma>
            <CharacterOffsetBegin>245</CharacterOffsetBegin>
            <CharacterOffsetEnd>247</CharacterOffsetEnd>
            <POS>IN</POS>
            <NER>O</NER>
          </token>
          <token id="46">
            <word>the</word>
            <lemma>the</lemma>
            <CharacterOffsetBegin>248</CharacterOffsetBegin>
            <CharacterOffsetEnd>251</CharacterOffsetEnd>
            <POS>DT</POS>
            <NER>O</NER>
          </token>
          <token id="47">
            <word>media</word>
            <lemma>media</lemma>
            <CharacterOffsetBegin>252</CharacterOffsetBegin>
            <CharacterOffsetEnd>257</CharacterOffsetEnd>
            <POS>NNS</POS>
            <NER>O</NER>
          </token>
          <token id="48">
            <word>giant</word>
            <lemma>giant</lemma>
            <CharacterOffsetBegin>258</CharacterOffsetBegin>
            <CharacterOffsetEnd>263</CharacterOffsetEnd>
            <POS>NN</POS>
            <NER>O</NER>
          </token>
          <token id="49">
            <word>.</word>
            <lemma>.</lemma>
            <CharacterOffsetBegin>263</CharacterOffsetBegin>
            <CharacterOffsetEnd>264</CharacterOffsetEnd>
            <POS>.</POS>
            <NER>O</NER>
          </token>
        </tokens>
      </sentence>
      <sentence id="2">
        <tokens>
          <token id="1">
            <word>Mr.</word>
            <lemma>Mr.</lemma>
            <CharacterOffsetBegin>265</CharacterOffsetBegin>
            <CharacterOffsetEnd>268</CharacterOffsetEnd>
            <POS>NNP</POS>
            <NER>PERSON</NER>
          </token>
          <token id="2">
            <word>Icahn</word>
            <lemma>Icahn</lemma>
            <CharacterOffsetBegin>269</CharacterOffsetBegin>
            <CharacterOffsetEnd>274</CharacterOffsetEnd>
            <POS>NNP</POS>
            <NER>PERSON</NER>
          </token>
          <token id="3">
            <word>,</word>
            <lemma>,</lemma>
            <CharacterOffsetBegin>274</CharacterOffsetBegin>
            <CharacterOffsetEnd>275</CharacterOffsetEnd>
            <POS>,</POS>
            <NER>O</NER>
          </token>
          <token id="4">
            <word>the</word>
            <lemma>the</lemma>
            <CharacterOffsetBegin>276</CharacterOffsetBegin>
            <CharacterOffsetEnd>279</CharacterOffsetEnd>
            <POS>DT</POS>
            <NER>O</NER>
          </token>
          <token id="5">
            <word>billionaire</word>
            <lemma>billionaire</lemma>
            <CharacterOffsetBegin>280</CharacterOffsetBegin>
            <CharacterOffsetEnd>291</CharacterOffsetEnd>
            <POS>NN</POS>
            <NER>O</NER>
          </token>
          <token id="6">
            <word>financier</word>
            <lemma>financier</lemma>
            <CharacterOffsetBegin>292</CharacterOffsetBegin>
            <CharacterOffsetEnd>301</CharacterOffsetEnd>
            <POS>NN</POS>
            <NER>O</NER>
          </token>
          <token id="7">
            <word>,</word>
            <lemma>,</lemma>
            <CharacterOffsetBegin>301</CharacterOffsetBegin>
            <CharacterOffsetEnd>302</CharacterOffsetEnd>
            <POS>,</POS>
            <NER>O</NER>
          </token>
          <token id="8">
            <word>has</word>
            <lemma>have</lemma>
            <CharacterOffsetBegin>303</CharacterOffsetBegin>
            <CharacterOffsetEnd>306</CharacterOffsetEnd>
            <POS>VBZ</POS>
            <NER>O</NER>
          </token>
          <token id="9">
            <word>been</word>
            <lemma>be</lemma>
            <CharacterOffsetBegin>307</CharacterOffsetBegin>
            <CharacterOffsetEnd>311</CharacterOffsetEnd>
            <POS>VBN</POS>
            <NER>O</NER>
          </token>
          <token id="10">
            <word>staging</word>
            <lemma>stage</lemma>
            <CharacterOffsetBegin>312</CharacterOffsetBegin>
            <CharacterOffsetEnd>319</CharacterOffsetEnd>
            <POS>VBG</POS>
            <NER>O</NER>
          </token>
          <token id="11">
            <word>a</word>
            <lemma>a</lemma>
            <CharacterOffsetBegin>320</CharacterOffsetBegin>
            <CharacterOffsetEnd>321</CharacterOffsetEnd>
            <POS>DT</POS>
            <NER>O</NER>
          </token>
          <token id="12">
            <word>battle</word>
            <lemma>battle</lemma>
            <CharacterOffsetBegin>322</CharacterOffsetBegin>
            <CharacterOffsetEnd>328</CharacterOffsetEnd>
            <POS>NN</POS>
            <NER>O</NER>
          </token>
          <token id="13">
            <word>to</word>
            <lemma>to</lemma>
            <CharacterOffsetBegin>329</CharacterOffsetBegin>
            <CharacterOffsetEnd>331</CharacterOffsetEnd>
            <POS>TO</POS>
            <NER>O</NER>
          </token>
          <token id="14">
            <word>replace</word>
            <lemma>replace</lemma>
            <CharacterOffsetBegin>332</CharacterOffsetBegin>
            <CharacterOffsetEnd>339</CharacterOffsetEnd>
            <POS>VB</POS>
            <NER>O</NER>
          </token>
          <token id="15">
            <word>the</word>
            <lemma>the</lemma>
            <CharacterOffsetBegin>340</CharacterOffsetBegin>
            <CharacterOffsetEnd>343</CharacterOffsetEnd>
            <POS>DT</POS>
            <NER>O</NER>
          </token>
          <token id="16">
            <word>board</word>
            <lemma>board</lemma>
            <CharacterOffsetBegin>344</CharacterOffsetBegin>
            <CharacterOffsetEnd>349</CharacterOffsetEnd>
            <POS>NN</POS>
            <NER>O</NER>
          </token>
          <token id="17">
            <word>of</word>
            <lemma>of</lemma>
            <CharacterOffsetBegin>350</CharacterOffsetBegin>
            <CharacterOffsetEnd>352</CharacterOffsetEnd>
            <POS>IN</POS>
            <NER>O</NER>
          </token>
          <token id="18">
            <word>Time</word>
            <lemma>Time</lemma>
            <CharacterOffsetBegin>353</CharacterOffsetBegin>
            <CharacterOffsetEnd>357</CharacterOffsetEnd>
            <POS>NNP</POS>
            <NER>ORGANIZATION</NER>
          </token>
          <token id="19">
            <word>Warner</word>
            <lemma>Warner</lemma>
            <CharacterOffsetBegin>358</CharacterOffsetBegin>
            <CharacterOffsetEnd>364</CharacterOffsetEnd>
            <POS>NNP</POS>
            <NER>ORGANIZATION</NER>
          </token>
          <token id="20">
            <word>,</word>
            <lemma>,</lemma>
            <CharacterOffsetBegin>364</CharacterOffsetBegin>
            <CharacterOffsetEnd>365</CharacterOffsetEnd>
            <POS>,</POS>
            <NER>O</NER>
          </token>
          <token id="21">
            <word>where</word>
            <lemma>where</lemma>
            <CharacterOffsetBegin>366</CharacterOffsetBegin>
            <CharacterOffsetEnd>371</CharacterOffsetEnd>
            <POS>WRB</POS>
            <NER>O</NER>
          </token>
          <token id="22">
            <word>his</word>
            <lemma>he</lemma>
            <CharacterOffsetBegin>372</CharacterOffsetBegin>
            <CharacterOffsetEnd>375</CharacterOffsetEnd>
            <POS>PRP$</POS>
            <NER>O</NER>
          </token>
          <token id="23">
            <word>fund</word>
            <lemma>fund</lemma>
            <CharacterOffsetBegin>376</CharacterOffsetBegin>
            <CharacterOffsetEnd>380</CharacterOffsetEnd>
            <POS>NN</POS>
            <NER>O</NER>
          </token>
          <token id="24">
            <word>and</word>
            <lemma>and</lemma>
            <CharacterOffsetBegin>381</CharacterOffsetBegin>
            <CharacterOffsetEnd>384</CharacterOffsetEnd>
            <POS>CC</POS>
            <NER>O</NER>
          </token>
          <token id="25">
            <word>various</word>
            <lemma>various</lemma>
            <CharacterOffsetBegin>385</CharacterOffsetBegin>
            <CharacterOffsetEnd>392</CharacterOffsetEnd>
            <POS>JJ</POS>
            <NER>O</NER>
          </token>
          <token id="26">
            <word>others</word>
            <lemma>other</lemma>
            <CharacterOffsetBegin>393</CharacterOffsetBegin>
            <CharacterOffsetEnd>399</CharacterOffsetEnd>
            <POS>NNS</POS>
            <NER>O</NER>
          </token>
          <token id="27">
            <word>own</word>
            <lemma>own</lemma>
            <CharacterOffsetBegin>400</CharacterOffsetBegin>
            <CharacterOffsetEnd>403</CharacterOffsetEnd>
            <POS>VBP</POS>
            <NER>O</NER>
          </token>
          <token id="28">
            <word>about</word>
            <lemma>about</lemma>
            <CharacterOffsetBegin>404</CharacterOffsetBegin>
            <CharacterOffsetEnd>409</CharacterOffsetEnd>
            <POS>RB</POS>
            <NER>O</NER>
          </token>
          <token id="29">
            <word>3</word>
            <lemma>3</lemma>
            <CharacterOffsetBegin>410</CharacterOffsetBegin>
            <CharacterOffsetEnd>411</CharacterOffsetEnd>
            <POS>CD</POS>
            <NER>PERCENT</NER>
            <NormalizedNER>~%3.0</NormalizedNER>
          </token>
          <token id="30">
            <word>percent</word>
            <lemma>percent</lemma>
            <CharacterOffsetBegin>412</CharacterOffsetBegin>
            <CharacterOffsetEnd>419</CharacterOffsetEnd>
            <POS>NN</POS>
            <NER>PERCENT</NER>
            <NormalizedNER>~%3.0</NormalizedNER>
          </token>
          <token id="31">
            <word>of</word>
            <lemma>of</lemma>
            <CharacterOffsetBegin>420</CharacterOffsetBegin>
            <CharacterOffsetEnd>422</CharacterOffsetEnd>
            <POS>IN</POS>
            <NER>O</NER>
          </token>
          <token id="32">
            <word>the</word>
            <lemma>the</lemma>
            <CharacterOffsetBegin>423</CharacterOffsetBegin>
            <CharacterOffsetEnd>426</CharacterOffsetEnd>
            <POS>DT</POS>
            <NER>O</NER>
          </token>
          <token id="33">
            <word>stock</word>
            <lemma>stock</lemma>
            <CharacterOffsetBegin>427</CharacterOffsetBegin>
            <CharacterOffsetEnd>432</CharacterOffsetEnd>
            <POS>NN</POS>
            <NER>O</NER>
          </token>
          <token id="34">
            <word>.</word>
            <lemma>.</lemma>
            <CharacterOffsetBegin>432</CharacterOffsetBegin>
            <CharacterOffsetEnd>433</CharacterOffsetEnd>
            <POS>.</POS>
            <NER>O</NER>
          </token>
        </tokens>
      </sentence>
      <sentence id="3">
        <tokens>
          <token id="1">
            <word>He</word>
            <lemma>he</lemma>
            <CharacterOffsetBegin>434</CharacterOffsetBegin>
            <CharacterOffsetEnd>436</CharacterOffsetEnd>
            <POS>PRP</POS>
            <NER>O</NER>
          </token>
          <token id="2">
            <word>has</word>
            <lemma>have</lemma>
            <CharacterOffsetBegin>437</CharacterOffsetBegin>
            <CharacterOffsetEnd>440</CharacterOffsetEnd>
            <POS>VBZ</POS>
            <NER>O</NER>
          </token>
          <token id="3">
            <word>told</word>
            <lemma>tell</lemma>
            <CharacterOffsetBegin>441</CharacterOffsetBegin>
            <CharacterOffsetEnd>445</CharacterOffsetEnd>
            <POS>VBN</POS>
            <NER>O</NER>
          </token>
          <token id="4">
            <word>other</word>
            <lemma>other</lemma>
            <CharacterOffsetBegin>446</CharacterOffsetBegin>
            <CharacterOffsetEnd>451</CharacterOffsetEnd>
            <POS>JJ</POS>
            <NER>O</NER>
          </token>
          <token id="5">
            <word>funds</word>
            <lemma>fund</lemma>
            <CharacterOffsetBegin>452</CharacterOffsetBegin>
            <CharacterOffsetEnd>457</CharacterOffsetEnd>
            <POS>NNS</POS>
            <NER>O</NER>
          </token>
          <token id="6">
            <word>that</word>
            <lemma>that</lemma>
            <CharacterOffsetBegin>458</CharacterOffsetBegin>
            <CharacterOffsetEnd>462</CharacterOffsetEnd>
            <POS>IN</POS>
            <NER>O</NER>
          </token>
          <token id="7">
            <word>he</word>
            <lemma>he</lemma>
            <CharacterOffsetBegin>463</CharacterOffsetBegin>
            <CharacterOffsetEnd>465</CharacterOffsetEnd>
            <POS>PRP</POS>
            <NER>O</NER>
          </token>
          <token id="8">
            <word>believes</word>
            <lemma>believe</lemma>
            <CharacterOffsetBegin>466</CharacterOffsetBegin>
            <CharacterOffsetEnd>474</CharacterOffsetEnd>
            <POS>VBZ</POS>
            <NER>O</NER>
          </token>
          <token id="9">
            <word>Time</word>
            <lemma>Time</lemma>
            <CharacterOffsetBegin>475</CharacterOffsetBegin>
            <CharacterOffsetEnd>479</CharacterOffsetEnd>
            <POS>NNP</POS>
            <NER>ORGANIZATION</NER>
          </token>
          <token id="10">
            <word>Warner</word>
            <lemma>Warner</lemma>
            <CharacterOffsetBegin>480</CharacterOffsetBegin>
            <CharacterOffsetEnd>486</CharacterOffsetEnd>
            <POS>NNP</POS>
            <NER>ORGANIZATION</NER>
          </token>
          <token id="11">
            <word>'s</word>
            <lemma>'s</lemma>
            <CharacterOffsetBegin>486</CharacterOffsetBegin>
            <CharacterOffsetEnd>488</CharacterOffsetEnd>
            <POS>POS</POS>
            <NER>O</NER>
          </token>
          <token id="12">
            <word>stock</word>
            <lemma>stock</lemma>
            <CharacterOffsetBegin>489</CharacterOffsetBegin>
            <CharacterOffsetEnd>494</CharacterOffsetEnd>
            <POS>NN</POS>
            <NER>O</NER>
          </token>
          <token id="13">
            <word>could</word>
            <lemma>could</lemma>
            <CharacterOffsetBegin>495</CharacterOffsetBegin>
            <CharacterOffsetEnd>500</CharacterOffsetEnd>
            <POS>MD</POS>
            <NER>O</NER>
          </token>
          <token id="14">
            <word>be</word>
            <lemma>be</lemma>
            <CharacterOffsetBegin>501</CharacterOffsetBegin>
            <CharacterOffsetEnd>503</CharacterOffsetEnd>
            <POS>VB</POS>
            <NER>O</NER>
          </token>
          <token id="15">
            <word>worth</word>
            <lemma>worth</lemma>
            <CharacterOffsetBegin>504</CharacterOffsetBegin>
            <CharacterOffsetEnd>509</CharacterOffsetEnd>
            <POS>JJ</POS>
            <NER>O</NER>
          </token>
          <token id="16">
            <word>about</word>
            <lemma>about</lemma>
            <CharacterOffsetBegin>510</CharacterOffsetBegin>
            <CharacterOffsetEnd>515</CharacterOffsetEnd>
            <POS>IN</POS>
            <NER>O</NER>
          </token>
          <token id="17">
            <word>$</word>
            <lemma>$</lemma>
            <CharacterOffsetBegin>516</CharacterOffsetBegin>
            <CharacterOffsetEnd>517</CharacterOffsetEnd>
            <POS>$</POS>
            <NER>MONEY</NER>
            <NormalizedNER>~$27.0</NormalizedNER>
          </token>
          <token id="18">
            <word>27</word>
            <lemma>27</lemma>
            <CharacterOffsetBegin>517</CharacterOffsetBegin>
            <CharacterOffsetEnd>519</CharacterOffsetEnd>
            <POS>CD</POS>
            <NER>MONEY</NER>
            <NormalizedNER>~$27.0</NormalizedNER>
          </token>
          <token id="19">
            <word>a</word>
            <lemma>a</lemma>
            <CharacterOffsetBegin>520</CharacterOffsetBegin>
            <CharacterOffsetEnd>521</CharacterOffsetEnd>
            <POS>DT</POS>
            <NER>O</NER>
          </token>
          <token id="20">
            <word>share</word>
            <lemma>share</lemma>
            <CharacterOffsetBegin>522</CharacterOffsetBegin>
            <CharacterOffsetEnd>527</CharacterOffsetEnd>
            <POS>NN</POS>
            <NER>O</NER>
          </token>
          <token id="21">
            <word>.</word>
            <lemma>.</lemma>
            <CharacterOffsetBegin>527</CharacterOffsetBegin>
            <CharacterOffsetEnd>528</CharacterOffsetEnd>
            <POS>.</POS>
            <NER>O</NER>
          </token>
        </tokens>
      </sentence>
    </sentences>
  </document>
</root>
